transmap/__init__.py
transmap/archive/ais/__init__.py
transmap/archive/ais/models.py
transmap/archive/ais/tracks.py
transmap/services/warnings.py
transmap/services/census/__init__.py
transmap/services/census/census_data.py
transmap/services/census/constants.py
transmap/services/cwbi/__init__.py
transmap/services/cwbi/constants.py
transmap/services/cwbi/locks.py
transmap/services/cwbi/models.py
transmap/services/data/__init__.py
transmap/services/data/data.py
transmap/services/lpms/__init__.py
transmap/services/lpms/constants.py
transmap/services/lpms/locks.py
transmap-0.4.1.dist-info/LICENSE
transmap-0.4.1.dist-info/METADATA
transmap-0.4.1.dist-info/WHEEL
transmap-0.4.1.dist-info/top_level.txt
transmap-0.4.1.dist-info/RECORD
