Metadata-Version: 2.1
Name: transmap
Version: 0.4.1
Summary: API for Transmap Hub
Author: Christopher C Angel, PhD
License: MIT
License-File: LICENSE
Requires-Dist: pandas
Requires-Dist: pytest
Requires-Dist: numpy (==1.19.3)
Requires-Dist: census
Requires-Dist: xmltodict
Requires-Dist: pydantic
Requires-Dist: requests
Requires-Dist: geojson
